thread_utils/_2captcha.py
thread_utils/__init__.py
thread_utils/printer.py
thread_utils/session_handler.py
thread_utils/threading.py
frenox_thread_utils-0.1.8.dist-info/LICENSE
frenox_thread_utils-0.1.8.dist-info/METADATA
frenox_thread_utils-0.1.8.dist-info/WHEEL
frenox_thread_utils-0.1.8.dist-info/top_level.txt
frenox_thread_utils-0.1.8.dist-info/RECORD
